which_bsm/__init__.py
which_bsm/_version.py
which_bsm/api.py
which_bsm/impl.py
which_bsm/paths.py
which_bsm/vendor/__init__.py
which_bsm/vendor/pytest_cov_helper.py
which_bsm-0.1.1.dist-info/AUTHORS.rst
which_bsm-0.1.1.dist-info/LICENSE.txt
which_bsm-0.1.1.dist-info/METADATA
which_bsm-0.1.1.dist-info/WHEEL
which_bsm-0.1.1.dist-info/RECORD
